MANIFEST.in
README.rst
bootstrap.py
setup.cfg
setup.py
test-plone-3.x.cfg
test-plone-4.0.x.cfg
test-plone-4.1.x.cfg
collective/__init__.py
collective.brasil.vocab.egg-info/PKG-INFO
collective.brasil.vocab.egg-info/SOURCES.txt
collective.brasil.vocab.egg-info/dependency_links.txt
collective.brasil.vocab.egg-info/entry_points.txt
collective.brasil.vocab.egg-info/namespace_packages.txt
collective.brasil.vocab.egg-info/not-zip-safe
collective.brasil.vocab.egg-info/requires.txt
collective.brasil.vocab.egg-info/top_level.txt
collective/brasil/__init__.py
collective/brasil/vocab/README.txt
collective/brasil/vocab/__init__.py
collective/brasil/vocab/config.py
collective/brasil/vocab/configure.zcml
collective/brasil/vocab/version.txt
collective/brasil/vocab/docs/__init__.py
collective/brasil/vocab/docs/browser.txt
collective/brasil/vocab/geo/__init__.py
collective/brasil/vocab/geo/cidades.py
collective/brasil/vocab/geo/configure.zcml
collective/brasil/vocab/geo/estados.py
collective/brasil/vocab/geo/paises.py
collective/brasil/vocab/telecom/__init__.py
collective/brasil/vocab/telecom/cng.py
collective/brasil/vocab/telecom/configure.zcml
collective/brasil/vocab/telecom/ddd.py
collective/brasil/vocab/tests/__init__.py
collective/brasil/vocab/tests/test_vocabularies.py
docs/HISTORY.txt
docs/LICENSE.GPL
docs/LICENSE.txt