Metadata-Version: 1.0
Name: collective.brasil.vocab
Version: 0.8
Summary: A Zope 3 vocabulary implementation of brasil.vocab
Home-page: https://github.com/simplesconsultoria/collective.brasil.vocab/
Author: Simples Consultoria <products@simplesconsultoria.com.br>
Author-email: products@simplesconsultoria.com.br
License: GPL
Keywords: zope brasil brazil vocabularies plone
Platform: UNKNOWN
Classifier: Framework :: Plone
Classifier: Framework :: Plone :: 3.3
Classifier: Framework :: Plone :: 4.0
Classifier: Framework :: Plone :: 4.1
Classifier: Framework :: Zope2
Classifier: Framework :: Zope3
Classifier: Intended Audience :: Developers
Classifier: Natural Language :: Portuguese (Brazilian)
Classifier: Programming Language :: Python
Classifier: Topic :: Software Development :: Libraries :: Python Modules
